wintheme/__init__.py
wintheme/blank.py
wintheme/flags.py
wintheme/wintheme.py
wintheme-1.0.1.dist-info/METADATA
wintheme-1.0.1.dist-info/WHEEL
wintheme-1.0.1.dist-info/top_level.txt
wintheme-1.0.1.dist-info/RECORD
